LICENSE
MANIFEST.in
README.md
pyproject.toml
setup.py
unifrac/__init__.py
unifrac/_api.c
unifrac/_api.pxd
unifrac/_api.pyx
unifrac/_meta.py
unifrac/_methods.py
unifrac.egg-info/PKG-INFO
unifrac.egg-info/SOURCES.txt
unifrac.egg-info/dependency_links.txt
unifrac.egg-info/requires.txt
unifrac.egg-info/top_level.txt
unifrac/tests/__init__.py
unifrac/tests/test_api.py
unifrac/tests/test_methods.py
unifrac/tests/data/crawford.biom
unifrac/tests/data/crawford.group.tsv
unifrac/tests/data/crawford.tre
unifrac/tests/data/e1.biom
unifrac/tests/data/e2.biom
unifrac/tests/data/t1.newick
unifrac/tests/data/t2.newick
unifrac/tests/data/test.faith.exp