Metadata-Version: 2.1
Name: unifrac
Version: 1.5
Summary: High performance phylogenetic diversity calculations
Home-page: https://github.com/biocore/unifrac
Author: Daniel McDonald
Author-email: wasade@gmail.com
License: BSD-3-Clause
Platform: UNKNOWN
Provides-Extra: test
Provides-Extra: all
License-File: LICENSE
